LogCenter/LogCenterLogger.py
LogCenter/LogCenterOptions.py
LogCenter/LogLevel.py
LogCenter/__init__.py
logcenter-0.1.5.dist-info/METADATA
logcenter-0.1.5.dist-info/WHEEL
logcenter-0.1.5.dist-info/top_level.txt
logcenter-0.1.5.dist-info/RECORD
