Metadata-Version: 2.2
Name: LogCenter
Version: 0.1.5
Summary: This lib will help you to send your app's logs to LogCenter.
Author-email: Hudson Ventura <hudsonventura@outlook.com>
Project-URL: Homepage, https://github.com/hudsonventura/LogCenter
Project-URL: Bug Tracker, https://github.com/hudsonventura/LogCenter/issues
Requires-Python: >=3.7
Requires-Dist: python-dateutil
Requires-Dist: uuid
Requires-Dist: requests
